aiohttp_socks_5
