Metadata-Version: 2.1
Name: aiohttp-socks-5
Version: 0.1.14
Summary: Full-featured proxy connector for aiohttp
Home-page: https://github.com/Skactor/aiohttp-proxy
Author: Skactor
Author-email: sk4ct0r@gmail.com
License: Apache 2
Keywords: asyncio aiohttp socks socks5 socks4 http https proxy aiofiles aiohttp cryptography
License-File: LICENSE.txt
